<?xml version="1.0" encoding="UTF-8"?><record_update>
    <sys_choice action="DELETE" field="u_request_type" table="x_58872_needit_needit" version="3">
        <sys_choice_set action="DELETE">
            <element>u_request_type</element>
            <name>x_58872_needit_needit</name>
            <sys_class_name/>
            <sys_created_by/>
            <sys_created_on/>
            <sys_id/>
            <sys_mod_count/>
            <sys_name/>
            <sys_package/>
            <sys_policy/>
            <sys_scope/>
            <sys_update_name/>
            <sys_updated_by/>
            <sys_updated_on>2019-10-09 13:22:04</sys_updated_on>
        </sys_choice_set>
    </sys_choice>
    <sys_update_version action="INSERT_OR_UPDATE">
        <action>DELETE</action>
        <application/>
        <file_path/>
        <instance_id>52191b53dbec730042b321c4059619c7</instance_id>
        <instance_name>dev79327</instance_name>
        <name>sys_choice_x_58872_needit_needit_u_request_type</name>
        <payload><![CDATA[<?xml version="1.0" encoding="UTF-8"?><record_update><sys_choice action="DELETE" field="u_request_type" table="x_58872_needit_needit" version="3"><sys_choice_set action="DELETE"><element>u_request_type</element><name>x_58872_needit_needit</name><sys_class_name/><sys_created_by/><sys_created_on/><sys_id/><sys_mod_count/><sys_name/><sys_package/><sys_policy/><sys_scope/><sys_update_name/><sys_updated_by/><sys_updated_on>2019-10-09 13:22:04</sys_updated_on></sys_choice_set></sys_choice></record_update>]]></payload>
        <payload_hash>1828161538</payload_hash>
        <record_name>x_58872_needit_needit.u_request_type</record_name>
        <reverted_from/>
        <source>237d08f2db14001031ab61ca0b96193e</source>
        <source_table>sys_update_set</source_table>
        <state>previous</state>
        <sys_created_by>admin</sys_created_by>
        <sys_created_on>2019-10-09 13:22:04</sys_created_on>
        <sys_id>56d3b50fdb90001031ab61ca0b96194c</sys_id>
        <sys_mod_count>0</sys_mod_count>
        <sys_recorded_at>16db0af0ac60000001</sys_recorded_at>
        <sys_updated_by>admin</sys_updated_by>
        <sys_updated_on>2019-10-09 13:22:04</sys_updated_on>
        <type>Choice list</type>
        <update_guid>52d3b50f40900010ba9eab057621f133</update_guid>
        <update_guid_history>52d3b50f40900010ba9eab057621f133:1828161538,1ed3b50f7990001053139eb3408b522f:-1340212031,9ad3b50fe19000100712c8b96371b42c:1611590076,1ad3b50f57900010bf5c8f2744ad7129:-2083158524,d0b1acfa7354001046cbe566edfd0365:1680630537</update_guid_history>
    </sys_update_version>
    <sys_metadata_delete action="INSERT_OR_UPDATE">
        <sys_audit_delete/>
        <sys_class_name>sys_metadata_delete</sys_class_name>
        <sys_created_by>admin</sys_created_by>
        <sys_created_on>2019-10-09 13:22:14</sys_created_on>
        <sys_db_object display_value="" name="sys_choice_set">sys_choice_set</sys_db_object>
        <sys_id>10e3390fdb90001031ab61ca0b961919</sys_id>
        <sys_metadata>10e3390fdb90001031ab61ca0b961919</sys_metadata>
        <sys_mod_count>0</sys_mod_count>
        <sys_name>u_request_type</sys_name>
        <sys_package display_value="NeedIt" source="x_58872_needit">6ead8e780f603200cd674f8ce1050ed1</sys_package>
        <sys_parent/>
        <sys_policy/>
        <sys_scope display_value="NeedIt">6ead8e780f603200cd674f8ce1050ed1</sys_scope>
        <sys_scope_delete display_value="">94872a8897db403e8ee69a431de2fca4</sys_scope_delete>
        <sys_update_name>sys_choice_x_58872_needit_needit_u_request_type</sys_update_name>
        <sys_update_version display_value="sys_choice_x_58872_needit_needit_u_request_type">56d3b50fdb90001031ab61ca0b96194c</sys_update_version>
        <sys_updated_by>admin</sys_updated_by>
        <sys_updated_on>2019-10-09 13:22:14</sys_updated_on>
    </sys_metadata_delete>
</record_update>
